dyn/benchmark/__init__.py
dyn/benchmark/assess.py
dyn/benchmark/metrics.py
dyn/benchmark/generator/__init__.py
dyn/benchmark/generator/_interfaces.py
dyn/benchmark/generator/communities_generator.py
dyn/benchmark/generator/edges_generator.py
dyn/benchmark/generator/events_generator.py
dyn/benchmark/generator/groundtruth_generator.py
dyn/benchmark/generator/nodes_generator.py
dyn_benchmark-0.6.0.dist-info/licenses/LICENSE
dyn_benchmark-0.6.0.dist-info/METADATA
dyn_benchmark-0.6.0.dist-info/WHEEL
dyn_benchmark-0.6.0.dist-info/top_level.txt
dyn_benchmark-0.6.0.dist-info/RECORD
